README.md
setup.py
pghipy/__init__.py
pghipy/pghipy.py
pghipy.egg-info/PKG-INFO
pghipy.egg-info/SOURCES.txt
pghipy.egg-info/dependency_links.txt
pghipy.egg-info/not-zip-safe
pghipy.egg-info/requires.txt
pghipy.egg-info/top_level.txt