Metadata-Version: 2.1
Name: pghipy
Version: 0.1.0
Summary: STFT/ISTFT transforms and phase recovery using Phase Gradient Heap Integration
Home-page: http://laurence.com.ar/pghipy
Author: Laurence Bender, Leonardo Pepino
Author-email: pghipy@gmail.com
License: MIT
Keywords: pghi,stft,istft,spectrogram,phase recovery
Platform: UNKNOWN
Classifier: Development Status :: 3 - Alpha
Classifier: Intended Audience :: Science/Research
Classifier: Intended Audience :: Developers
Classifier: Natural Language :: English
Classifier: License :: OSI Approved :: MIT License
Classifier: Operating System :: Microsoft :: Windows :: Windows 10
Classifier: Operating System :: MacOS :: MacOS X
Classifier: Operating System :: POSIX :: Linux
Classifier: Programming Language :: Python :: 3.6
Classifier: Programming Language :: Python :: 3.7
Classifier: Programming Language :: Python :: 3.8
Classifier: Topic :: Scientific/Engineering
Requires-Python: >=3.6
